{"nodes": [{"id": "knowledge_library_k-8eb2ddfd", "label": "\uace8\ud504\uc874\uc758 \ud575\uc2ec \uae30\uc220 \uc81c\ud488\uad70 \ubc0f \ud2b9\uc9d5", "file_type": "document", "source_file": "knowledge/library/K-8EB2DDFD.md", "source_location": null, "source_url": null, "captured_at": null, "author": null, "contributor": null}], "edges": [{"source": "knowledge_library_k-8eb2ddfd", "target": "knowledge_library_k-1f22bb3d", "relation": "shares_data_with", "confidence": "INFERRED", "confidence_score": 1.0, "source_file": "knowledge/library/K-8EB2DDFD.md", "source_location": null, "weight": 1.0}, {"source": "knowledge_library_k-8eb2ddfd", "target": "unreal_engine_5", "relation": "conceptually_related_to", "confidence": "EXTRACTED", "confidence_score": 1.0, "source_file": "knowledge/library/K-8EB2DDFD.md", "source_location": null, "weight": 1.0}, {"source": "knowledge_library_k-8eb2ddfd", "target": "ai", "relation": "conceptually_related_to", "confidence": "EXTRACTED", "confidence_score": 1.0, "source_file": "knowledge/library/K-8EB2DDFD.md", "source_location": null, "weight": 1.0}], "hyperedges": []}